lucas_check_os_ver-0.3.5.dist-info/METADATA
lucas_check_os_ver-0.3.5.dist-info/WHEEL
lucas_check_os_ver-0.3.5.dist-info/entry_points.txt
lucas_check_os_ver/__init__.py
lucas_check_os_ver/hi.py
lucas_check_os_ver-0.3.5.dist-info/RECORD
